<?xml version='1.0' encoding='utf-8'?>
<mets xmlns:xlink="http://www.w3.org/1999/xlink" xmlns="http://www.loc.gov/METS/">
  <dmdSec ID="case">
    <mdWrap MDTYPE="OTHER" OTHERMDTYPE="HLS-CASELAW-CASEXML">
      <xmlData>
        <case xmlns="http://nrs.harvard.edu/urn-3:HLS.Libr.US_Case_Law.Schema.Case:v1" caseid="32044078577194_0129" publicationstatus="published">
          <court abbreviation="Ark." jurisdiction="Arkansas">Arkansas Supreme Court</court>
          <name abbreviation="Vanderkamp v. State">Diana Jean VANDERKAMP et al. v. STATE of Arkansas</name>
          <docketnumber/>
          <citation category="official" type="bluebook">288 Ark. 531</citation>
          <citation category="parallel" type="bluebook">706 S.W.2d 396</citation>
          <decisiondate>1986-04-14</decisiondate>
        </case>
      </xmlData>
    </mdWrap>
  </dmdSec>
  <amdSec ID="amd0001">
    <digiprovMD ID="digi001">
      <mdWrap MDTYPE="PREMIS">
        <xmlData>
          <event xmlns="info:lc/xmlns/premis-v2">
            <eventIdentifier>
              <eventIdentifierType>Local</eventIdentifierType>
              <eventIdentifierValue>scn0001</eventIdentifierValue>
            </eventIdentifier>
            <eventType>capture</eventType>
            <eventDateTime>2016-03-18T23:23:05Z</eventDateTime>
            <eventDetail>Scan date noting when printed source volume was converted to digital images used as sources for transcription.</eventDetail>
          </event>
          <agent xmlns="info:lc/xmlns/premis-v2">
            <agentIdentifier>
              <agentIdentifierType>Local</agentIdentifierType>
              <agentIdentifierValue>HLSL</agentIdentifierValue>
            </agentIdentifier>
            <agentName>Harvard Law School Library</agentName>
            <agentType>organization</agentType>
          </agent>
        </xmlData>
      </mdWrap>
    </digiprovMD>
    <digiprovMD ID="digi002">
      <mdWrap MDTYPE="PREMIS">
        <xmlData>
          <event xmlns="info:lc/xmlns/premis-v2">
            <eventIdentifier>
              <eventIdentifierType>Local</eventIdentifierType>
              <eventIdentifierValue>ocr0001</eventIdentifierValue>
            </eventIdentifier>
            <eventType>transcription</eventType>
            <eventDateTime>2017-03-22T06:15:00Z</eventDateTime>
            <eventDetail>Transcription event</eventDetail>
          </event>
          <agent xmlns="info:lc/xmlns/premis-v2">
            <agentIdentifier>
              <agentIdentifierType>Local</agentIdentifierType>
              <agentIdentifierValue>dsrs</agentIdentifierValue>
            </agentIdentifier>
            <agentName>Innodata DSRS, ABBYY FineReader</agentName>
            <agentType>software</agentType>
            <agentNote>Version 10</agentNote>
          </agent>
        </xmlData>
      </mdWrap>
    </digiprovMD>
    <digiprovMD ID="digi003">
      <mdWrap MDTYPE="PREMIS">
        <xmlData>
          <event xmlns="info:lc/xmlns/premis-v2">
            <eventIdentifier>
              <eventIdentifierType>Local</eventIdentifierType>
              <eventIdentifierValue>crt0001</eventIdentifierValue>
            </eventIdentifier>
            <eventType>METScreation</eventType>
            <eventDateTime>2017-04-25T06:27:44Z</eventDateTime>
            <eventDetail>Creation of digital artifact described by this METS file</eventDetail>
          </event>
          <agent xmlns="info:lc/xmlns/premis-v2">
            <agentIdentifier>
              <agentIdentifierType>Local</agentIdentifierType>
              <agentIdentifierValue>redrli</agentIdentifierValue>
            </agentIdentifier>
            <agentName>Innodata R.E.D. Workbench/RLI tool</agentName>
            <agentType>software</agentType>
            <agentNote>Version 20170308.post165</agentNote>
          </agent>
        </xmlData>
      </mdWrap>
    </digiprovMD>
    <digiprovMD ID="digi004">
      <mdWrap MDTYPE="PREMIS">
        <xmlData>
          <event xmlns="info:lc/xmlns/premis-v2">
            <eventIdentifier>
              <eventIdentifierType>Local</eventIdentifierType>
              <eventIdentifierValue>red0001</eventIdentifierValue>
            </eventIdentifier>
            <eventType>redaction</eventType>
            <eventDateTime>2017-04-25T06:32:01Z</eventDateTime>
            <eventDetail>Redaction step</eventDetail>
          </event>
          <agent xmlns="info:lc/xmlns/premis-v2">
            <agentIdentifier>
              <agentIdentifierType>Local</agentIdentifierType>
              <agentIdentifierValue>redravel-redactor</agentIdentifierValue>
            </agentIdentifier>
            <agentName>Innodata R.E.D. Workbench/RLI tool</agentName>
            <agentType>software</agentType>
            <agentNote>Version 20170308.post165</agentNote>
          </agent>
        </xmlData>
      </mdWrap>
    </digiprovMD>
  </amdSec>
  <fileSec>
    <fileGrp USE="tiff">
      <file ID="tiff_00285_0" MIMETYPE="image/tiff" CHECKSUM="468a4fe3a5b5b7a5556ccc51b736e234" CHECKSUMTYPE="MD5" SIZE="20106">
        <FLocat LOCTYPE="URL" xlink:href="../images/32044078577194_00285_0.tif"/>
      </file>
    </fileGrp>
    <fileGrp USE="jp2">
      <file ID="jp2_00285_0" MIMETYPE="image/jp2" CHECKSUM="4c8ef5f3fdda4b89fddcf43d0968d6ff" CHECKSUMTYPE="MD5" SIZE="2137503">
        <FLocat LOCTYPE="URL" xlink:href="../images/32044078577194_00285_0.jp2"/>
      </file>
    </fileGrp>
    <fileGrp USE="alto">
      <file ID="alto_00285_0" MIMETYPE="text/xml" CHECKSUM="81b620f9fa9d5c4167aa4978ac387848" CHECKSUMTYPE="MD5" SIZE="33463">
        <FLocat LOCTYPE="URL" xlink:href="../alto/32044078577194_redacted_ALTO_00285_0.xml"/>
      </file>
    </fileGrp>
    <fileGrp USE="casebody">
      <file ID="casebody_0129" MIMETYPE="text/xml">
        <FContent>
          <xmlData>
            <casebody xmlns="http://nrs.harvard.edu/urn-3:HLS.Libr.US_Case_Law.Schema.Case_Body:v1" firstpage="531" lastpage="531">
              <court pgmap="569" id="b569-4">Supreme Court of Arkansas</court>
              <citation pgmap="569" id="b569-3">706 S.W.2d 396</citation>
              <parties pgmap="569" id="b569-2">Diana Jean VANDERKAMP et al. v. STATE of Arkansas</parties>
              <decisiondate pgmap="569" id="Abh">Opinion delivered April 14, 1986</decisiondate>
              <judges pgmap="569" id="b569-14">Purtle, J., not participating.</judges>
              <attorneys pgmap="569" id="b569-9">James E. Davis, for appellants.</attorneys>
              <attorneys pgmap="569" id="b569-10">Steve Clark, Att’y Gen., by: Theodore Holder, Asst. Att’y Gen., for appellee.</attorneys>
              <opinion type="majority">
                <author pgmap="569" id="b569-11">Per Curiam.</author>
                <p pgmap="569" id="Aq6">The appellants have filed a motion for a rule to require the Clerk to file the record in this case. It appears that the record was tendered a day late. The appellants’ attorney, James E. Davis, accepts full responsibility for the delay.</p>
                <p pgmap="569" id="b569-12">
                   This is a sufficient reason for accepting the record. See our per curiam opinion of February 5, 1979. 265 Ark. 964. The motion is accordingly granted.</p>
                <p pgmap="569" id="b569-13">A copy of this opinion will be sent to the Committee on Professional Conduct.</p>
              </opinion>
            </casebody>
          </xmlData>
        </FContent>
      </file>
    </fileGrp>
  </fileSec>
  <structMap TYPE="physical">
    <div TYPE="volume">
      <div ORDER="569" ORDERLABEL="531" TYPE="page">
        <fptr FILEID="tiff_00285_0"/>
        <fptr FILEID="jp2_00285_0"/>
        <fptr FILEID="alto_00285_0"/>
        <div TYPE="pagelabel">
          <fptr>
            <seq>
              <area BEGIN="BL_569.2" BETYPE="IDREF" FILEID="alto_00285_0"/>
            </seq>
          </fptr>
        </div>
      </div>
    </div>
  </structMap>
  <structMap TYPE="xref">
    <div TYPE="blocks">
      <div TYPE="element">
        <fptr>
          <area BEGIN="b569-14" BETYPE="IDREF" FILEID="casebody_0129"/>
        </fptr>
        <fptr>
          <seq>
            <area BEGIN="BL_569.17" BETYPE="IDREF" FILEID="alto_00285_0"/>
          </seq>
        </fptr>
      </div>
      <div TYPE="element">
        <fptr>
          <area BEGIN="b569-12" BETYPE="IDREF" FILEID="casebody_0129"/>
        </fptr>
        <fptr>
          <seq>
            <area BEGIN="BL_569.15" BETYPE="IDREF" FILEID="alto_00285_0"/>
          </seq>
        </fptr>
      </div>
      <div TYPE="element">
        <fptr>
          <area BEGIN="b569-13" BETYPE="IDREF" FILEID="casebody_0129"/>
        </fptr>
        <fptr>
          <seq>
            <area BEGIN="BL_569.16" BETYPE="IDREF" FILEID="alto_00285_0"/>
          </seq>
        </fptr>
      </div>
      <div TYPE="element">
        <fptr>
          <area BEGIN="b569-10" BETYPE="IDREF" FILEID="casebody_0129"/>
        </fptr>
        <fptr>
          <seq>
            <area BEGIN="BL_569.11" BETYPE="IDREF" FILEID="alto_00285_0"/>
          </seq>
        </fptr>
      </div>
      <div TYPE="element">
        <fptr>
          <area BEGIN="b569-11" BETYPE="IDREF" FILEID="casebody_0129"/>
        </fptr>
        <fptr>
          <seq>
            <area BEGIN="BL_569.12" BETYPE="IDREF" FILEID="alto_00285_0"/>
          </seq>
        </fptr>
      </div>
      <div TYPE="element">
        <fptr>
          <area BEGIN="b569-4" BETYPE="IDREF" FILEID="casebody_0129"/>
        </fptr>
        <fptr>
          <seq>
            <area BEGIN="BL_569.5" BETYPE="IDREF" FILEID="alto_00285_0"/>
          </seq>
        </fptr>
      </div>
      <div TYPE="element">
        <fptr>
          <area BEGIN="Aq6" BETYPE="IDREF" FILEID="casebody_0129"/>
        </fptr>
        <fptr>
          <seq>
            <area BEGIN="BL_569.13" BETYPE="IDREF" FILEID="alto_00285_0"/>
            <area BEGIN="BL_569.14" BETYPE="IDREF" FILEID="alto_00285_0"/>
          </seq>
        </fptr>
      </div>
      <div TYPE="element">
        <fptr>
          <area BEGIN="b569-2" BETYPE="IDREF" FILEID="casebody_0129"/>
        </fptr>
        <fptr>
          <seq>
            <area BEGIN="BL_569.3" BETYPE="IDREF" FILEID="alto_00285_0"/>
          </seq>
        </fptr>
      </div>
      <div TYPE="element">
        <fptr>
          <area BEGIN="b569-3" BETYPE="IDREF" FILEID="casebody_0129"/>
        </fptr>
        <fptr>
          <seq>
            <area BEGIN="BL_569.4" BETYPE="IDREF" FILEID="alto_00285_0"/>
          </seq>
        </fptr>
      </div>
      <div TYPE="element">
        <fptr>
          <area BEGIN="b569-9" BETYPE="IDREF" FILEID="casebody_0129"/>
        </fptr>
        <fptr>
          <seq>
            <area BEGIN="BL_569.10" BETYPE="IDREF" FILEID="alto_00285_0"/>
          </seq>
        </fptr>
      </div>
      <div TYPE="element">
        <fptr>
          <area BEGIN="Abh" BETYPE="IDREF" FILEID="casebody_0129"/>
        </fptr>
        <fptr>
          <seq>
            <area BEGIN="BL_569.6" BETYPE="IDREF" FILEID="alto_00285_0"/>
          </seq>
        </fptr>
      </div>
    </div>
  </structMap>
</mets>
